structureReader/__init__.py
structureReader/structureReader.py
structureReader-2.1.11.dist-info/METADATA
structureReader-2.1.11.dist-info/WHEEL
structureReader-2.1.11.dist-info/top_level.txt
structureReader-2.1.11.dist-info/RECORD
